setup.py
make_box/__init__.py
make_box/prompt_box.py
make_box/test.py
prompt_box.egg-info/PKG-INFO
prompt_box.egg-info/SOURCES.txt
prompt_box.egg-info/dependency_links.txt
prompt_box.egg-info/top_level.txt