Metadata-Version: 1.0
Name: prompt-box
Version: 0.0.1
Summary: shortcuts for basic and advanced message boxes
Home-page: UNKNOWN
Author: UNKNOWN
Author-email: UNKNOWN
License: UNKNOWN
Platform: UNKNOWN
